checkptr/__init__.py
checkptr/main.py
checkptr-0.1.3.dist-info/METADATA
checkptr-0.1.3.dist-info/WHEEL
checkptr-0.1.3.dist-info/top_level.txt
checkptr-0.1.3.dist-info/RECORD
