Metadata-Version: 2.1
Name: checkptr
Version: 0.1.3
Summary: Simple standard for model checkpointing, framework-agnostic
Author-email: Marcel Claramunt <marcel@moveread.com>
Project-URL: repo, https://github.com/moveread/REPO.git
Requires-Python: >=3.10
